himpunan/__init__.py
himpunan/himpunan.py
himpunan_group1_ucmakassar-1.0.0.dist-info/METADATA
himpunan_group1_ucmakassar-1.0.0.dist-info/WHEEL
himpunan_group1_ucmakassar-1.0.0.dist-info/top_level.txt
himpunan_group1_ucmakassar-1.0.0.dist-info/RECORD
