Metadata-Version: 2.4
Name: himpunan-group1-ucmakassar
Version: 1.0.0
Summary: A simple Python library for set operations (Himpunan) supporting fractions and decimals.
Home-page: https://github.com/mchlstvny/himpunan-project-discrete-mathematics.git
Author: Kelompok 2
Author-email: Group 1 <mchlstvny@gmail.com>
License: MIT
Project-URL: Homepage, https://github.com/mchlstvny/himpunan-project-discrete-mathematics.git
Keywords: himpunan,set,mathematics,fraction,decimal
Classifier: Programming Language :: Python :: 3
Classifier: License :: OSI Approved :: MIT License
Classifier: Operating System :: OS Independent
Requires-Python: >=3.8
Dynamic: author
Dynamic: home-page
